skutils/__init__.py
skutils/skutils.py
skutils-0.1.0.dist-info/DESCRIPTION.rst
skutils-0.1.0.dist-info/METADATA
skutils-0.1.0.dist-info/RECORD
skutils-0.1.0.dist-info/WHEEL
skutils-0.1.0.dist-info/metadata.json
skutils-0.1.0.dist-info/top_level.txt
